{
  "characters": [
    {
      "id": 1,
      "name": "Superman",
      "source": "DC Comics",
      "gender": "male",
      "value": 2000,
      "image": "https://placeholder.com/superman.jpg",
      "vid": "https://placeholder.com/superman_video.mp4",
      "status": "libre",
      "user": null,
      "votes": 0,
      "habilidad": "Super fuerza, vuelo, visión de calor, invulnerabilidad",
      "debilidad": "Kryptonita, magia, radiación solar roja"
    },
    {
      "id": 2,
      "name": "Batman",
      "source": "DC Comics",
      "gender": "male",
      "value": 1950,
      "image": "https://placeholder.com/batman.jpg",
      "vid": "https://placeholder.com/batman_video.mp4",
      "status": "libre",
      "user": null,
      "votes": 0,
      "habilidad": "Genio intelectual, artes marciales, tecnología avanzada",
      "debilidad": "Sin superpoderes, traumatizado por la muerte de sus padres"
    },
    {
      "id": 3,
      "name": "Wonder Woman",
      "source": "DC Comics",
      "gender": "female",
      "value": 1900,
      "image": "https://placeholder.com/wonderwoman.jpg",
      "vid": "https://placeholder.com/wonderwoman_video.mp4",
      "status": "libre",
      "user": null,
      "votes": 0,
      "habilidad": "Super fuerza, lazo de la verdad, bracelets deflectores",
      "debilidad": "Ataduras por un hombre, pérdida de poderes sin bracelets"
    },
    {
      "id": 4,
      "name": "The Flash",
      "source": "DC Comics",
      "gender": "male",
      "value": 1800,
      "image": "https://placeholder.com/flash.jpg",
      "vid": "https://placeholder.com/flash_video.mp4",
      "status": "libre",
      "user": null,
      "votes": 0,
      "habilidad": "Super velocidad, viaje en el tiempo, Speed Force",
      "debilidad": "Frío extremo, necesita consumir muchas calorías"
    },
    {
      "id": 5,
      "name": "Green Lantern",
      "source": "DC Comics",
      "gender": "male",
      "value": 1700,
      "image": "https://placeholder.com/greenlantern.jpg",
      "vid": "https://placeholder.com/greenlantern_video.mp4",
      "status": "libre",
      "user": null,
      "votes": 0,
      "habilidad": "Anillo de poder, construcciones de energía verde",
      "debilidad": "Color amarillo, necesita recarga del anillo"
    },
    {
      "id": 6,
      "name": "Aquaman",
      "source": "DC Comics",
      "gender": "male",
      "value": 1600,
      "image": "https://placeholder.com/aquaman.jpg",
      "vid": "https://placeholder.com/aquaman_video.mp4",
      "status": "libre",
      "user": null,
      "votes": 0,
      "habilidad": "Comunicación con vida marina, super fuerza submarina",
      "debilidad": "Necesita agua regularmente, menos poderoso en tierra"
    },
    {
      "id": 7,
      "name": "Joker",
      "source": "DC Comics",
      "gender": "male",
      "value": 1850,
      "image": "https://placeholder.com/joker.jpg",
      "vid": "https://placeholder.com/joker_video.mp4",
      "status": "libre",
      "user": null,
      "votes": 0,
      "habilidad": "Genio criminal, impredecibilidad, gas de la risa",
      "debilidad": "Locura, obsesión con Batman"
    },
    {
      "id": 8,
      "name": "Harley Quinn",
      "source": "DC Comics",
      "gender": "female",
      "value": 1650,
      "image": "https://placeholder.com/harleyquinn.jpg",
      "vid": "https://placeholder.com/harleyquinn_video.mp4",
      "status": "libre",
      "user": null,
      "votes": 0,
      "habilidad": "Agilidad acrobática, resistencia a toxinas, combate",
      "debilidad": "Inestabilidad mental, obsesión con Joker"
    },
    {
      "id": 9,
      "name": "Catwoman",
      "source": "DC Comics",
      "gender": "female",
      "value": 1400,
      "image": "https://placeholder.com/catwoman.jpg",
      "vid": "https://placeholder.com/catwoman_video.mp4",
      "status": "libre",
      "user": null,
      "votes": 0,
      "habilidad": "Agilidad felina, sigilo, maestría en robo",
      "debilidad": "Sin superpoderes, conflicto moral con Batman"
    },
    {
      "id": 10,
      "name": "Lex Luthor",
      "source": "DC Comics",
      "gender": "male",
      "value": 1750,
      "image": "https://placeholder.com/lexluthor.jpg",
      "vid": "https://placeholder.com/lexluthor_video.mp4",
      "status": "libre",
      "user": null,
      "votes": 0,
      "habilidad": "Super genio, riqueza, tecnología avanzada",
      "debilidad": "Obsesión con Superman, arrogancia"
    },
    {
      "id": 11,
      "name": "Cyborg",
      "source": "DC Comics",
      "gender": "male",
      "value": 1500,
      "image": "https://placeholder.com/cyborg.jpg",
      "vid": "https://placeholder.com/cyborg_video.mp4",
      "status": "libre",
      "user": null,
      "votes": 0,
      "habilidad": "Tecnología cibernética, cañones de sonido, interfaz digital",
      "debilidad": "Vulnerabilidad a EMP, dependencia tecnológica"
    },
    {
      "id": 12,
      "name": "Green Arrow",
      "source": "DC Comics",
      "gender": "male",
      "value": 1200,
      "image": "https://placeholder.com/greenarrow.jpg",
      "vid": "https://placeholder.com/greenarrow_video.mp4",
      "status": "libre",
      "user": null,
      "votes": 0,
      "habilidad": "Maestría en arquería, flechas especializadas",
      "debilidad": "Sin superpoderes, alcance limitado"
    },
    {
      "id": 13,
      "name": "Black Canary",
      "source": "DC Comics",
      "gender": "female",
      "value": 1100,
      "image": "https://placeholder.com/blackcanary.jpg",
      "vid": "https://placeholder.com/blackcanary_video.mp4",
      "status": "libre",
      "user": null,
      "votes": 0,
      "habilidad": "Grito ultrasónico, artes marciales",
      "debilidad": "Vulnerable cuando no puede gritar, alcance limitado"
    },
    {
      "id": 14,
      "name": "Martian Manhunter",
      "source": "DC Comics",
      "gender": "male",
      "value": 1600,
      "image": "https://placeholder.com/martianmanhunter.jpg",
      "vid": "https://placeholder.com/martianmanhunter_video.mp4",
      "status": "libre",
      "user": null,
      "votes": 0,
      "habilidad": "Cambio de forma, telepatía, invisibilidad, super fuerza",
      "debilidad": "Fuego, vulnerable psicológicamente"
    },
    {
      "id": 15,
      "name": "Shazam",
      "source": "DC Comics",
      "gender": "male",
      "value": 1550,
      "image": "https://placeholder.com/shazam.jpg",
      "vid": "https://placeholder.com/shazam_video.mp4",
      "status": "libre",
      "user": null,
      "votes": 0,
      "habilidad": "Poderes mágicos, super fuerza, vuelo, rayos",
      "debilidad": "Decir 'Shazam' lo convierte en niño, magia"
    },
    {
      "id": 16,
      "name": "Poison Ivy",
      "source": "DC Comics",
      "gender": "female",
      "value": 1300,
      "image": "https://placeholder.com/poisonivy.jpg",
      "vid": "https://placeholder.com/poisonivy_video.mp4",
      "status": "libre",
      "user": null,
      "votes": 0,
      "habilidad": "Control de plantas, toxinas, feromonas",
      "debilidad": "Fuego, herbicidas, ambientes sin plantas"
    },
    {
      "id": 17,
      "name": "Deathstroke",
      "source": "DC Comics",
      "gender": "male",
      "value": 1450,
      "image": "https://placeholder.com/deathstroke.jpg",
      "vid": "https://placeholder.com/deathstroke_video.mp4",
      "status": "libre",
      "user": null,
      "votes": 0,
      "habilidad": "Súper soldado mejorado, maestría en combate",
      "debilidad": "Ceguera en un ojo, arrogancia"
    },
    {
      "id": 18,
      "name": "Raven",
      "source": "DC Comics",
      "gender": "female",
      "value": 1350,
      "image": "https://placeholder.com/raven.jpg",
      "vid": "https://placeholder.com/raven_video.mp4",
      "status": "libre",
      "user": null,
      "votes": 0,
      "habilidad": "Magia demoníaca, teletransporte, energía oscura",
      "debilidad": "Emociones intensas, herencia demoníaca"
    },
    {
      "id": 19,
      "name": "Starfire",
      "source": "DC Comics",
      "gender": "female",
      "value": 1250,
      "image": "https://placeholder.com/starfire.jpg",
      "vid": "https://placeholder.com/starfire_video.mp4",
      "status": "libre",
      "user": null,
      "votes": 0,
      "habilidad": "Vuelo, ráfagas de energía, super fuerza",
      "debilidad": "Emociones controlan sus poderes, ingenuidad"
    },
    {
      "id": 20,
      "name": "Robin",
      "source": "DC Comics",
      "gender": "male",
      "value": 1000,
      "image": "https://placeholder.com/robin.jpg",
      "vid": "https://placeholder.com/robin_video.mp4",
      "status": "libre",
      "user": null,
      "votes": 0,
      "habilidad": "Acrobacia, artes marciales, tecnología",
      "debilidad": "Sin superpoderes, inexperiencia por juventud"
    },
    {
      "id": 21,
      "name": "Nightwing",
      "source": "DC Comics",
      "gender": "male",
      "value": 1400,
      "image": "https://placeholder.com/nightwing.jpg",
      "vid": "https://placeholder.com/nightwing_video.mp4",
      "status": "libre",
      "user": null,
      "votes": 0,
      "habilidad": "Acrobacia experta, liderazgo, bastones eléctricos",
      "debilidad": "Sin superpoderes, a veces demasiado independiente"
    },
    {
      "id": 22,
      "name": "Batgirl",
      "source": "DC Comics",
      "gender": "female",
      "value": 1150,
      "image": "https://placeholder.com/batgirl.jpg",
      "vid": "https://placeholder.com/batgirl_video.mp4",
      "status": "libre",
      "user": null,
      "votes": 0,
      "habilidad": "Genio en computación, artes marciales, detective",
      "debilidad": "Sin superpoderes, paralización pasada"
    },
    {
      "id": 23,
      "name": "Zatanna",
      "source": "DC Comics",
      "gender": "female",
      "value": 1500,
      "image": "https://placeholder.com/zatanna.jpg",
      "vid": "https://placeholder.com/zatanna_video.mp4",
      "status": "libre",
      "user": null,
      "votes": 0,
      "habilidad": "Magia hablando al revés, ilusionismo",
      "debilidad": "No puede hablar para lanzar hechizos, magia limitada"
    },
    {
      "id": 24,
      "name": "Doctor Fate",
      "source": "DC Comics",
      "gender": "male",
      "value": 1800,
      "image": "https://placeholder.com/doctorfate.jpg",
      "vid": "https://placeholder.com/doctorfate_video.mp4",
      "status": "libre",
      "user": null,
      "votes": 0,
      "habilidad": "Magia del Orden, casco de Nabu, vuelo",
      "debilidad": "Dependencia del casco, conflicto con Nabu"
    },
    {
      "id": 25,
      "name": "Hawkgirl",
      "source": "DC Comics",
      "gender": "female",
      "value": 1200,
      "image": "https://placeholder.com/hawkgirl.jpg",
      "vid": "https://placeholder.com/hawkgirl_video.mp4",
      "status": "libre",
      "user": null,
      "votes": 0,
      "habilidad": "Vuelo, maza de Nth metal, reencarnación",
      "debilidad": "Recuerdos de vidas pasadas, dependencia de alas"
    },
    {
      "id": 26,
      "name": "Constantine",
      "source": "DC Comics",
      "gender": "male",
      "value": 1350,
      "image": "https://placeholder.com/constantine.jpg",
      "vid": "https://placeholder.com/constantine_video.mp4",
      "status": "libre",
      "user": null,
      "votes": 0,
      "habilidad": "Magia, conocimiento oculto, manipulación",
      "debilidad": "Cáncer, enemigos demoniacos, moral ambigua"
    },
    {
      "id": 27,
      "name": "Supergirl",
      "source": "DC Comics",
      "gender": "female",
      "value": 1700,
      "image": "https://placeholder.com/supergirl.jpg",
      "vid": "https://placeholder.com/supergirl_video.mp4",
      "status": "libre",
      "user": null,
      "votes": 0,
      "habilidad": "Poderes kryptonianos, vuelo, super fuerza",
      "debilidad": "Kryptonita, magia, radiación solar roja"
    },
    {
      "id": 28,
      "name": "Black Adam",
      "source": "DC Comics",
      "gender": "male",
      "value": 1650,
      "image": "https://placeholder.com/blackadam.jpg",
      "vid": "https://placeholder.com/blackadam_video.mp4",
      "status": "libre",
      "user": null,
      "votes": 0,
      "habilidad": "Poderes de Shazam, experiencia milenaria",
      "debilidad": "Palabra mágica, arrogancia, ira"
    },
    {
      "id": 29,
      "name": "Power Girl",
      "source": "DC Comics",
      "gender": "female",
      "value": 1450,
      "image": "https://placeholder.com/powergirl.jpg",
      "vid": "https://placeholder.com/powergirl_video.mp4",
      "status": "libre",
      "user": null,
      "votes": 0,
      "habilidad": "Poderes kryptonianos, personalidad fuerte",
      "debilidad": "Radiación natural, temperamento impulsivo"
    },
    {
      "id": 30,
      "name": "Darkseid",
      "source": "DC Comics",
      "gender": "male",
      "value": 1950,
      "image": "https://placeholder.com/darkseid.jpg",
      "vid": "https://placeholder.com/darkseid_video.mp4",
      "status": "libre",
      "user": null,
      "votes": 0,
      "habilidad": "Rayos Omega, super fuerza cósmica, inmortalidad",
      "debilidad": "Ecuación Anti-Vida, dependencia de parademons"
    }
  ]
}
